{
  "profiles": {
    "tcp|android-h2|eth:Ethernet": {
      "success_count": 0,
      "fail_count": 3,
      "last_rtt_ms": 0,
      "score": 0,
      "updated_at": 1771097740
    },
    "tcp|google-ff|eth:Ethernet": {
      "success_count": 0,
      "fail_count": 3,
      "last_rtt_ms": 0,
      "score": 0,
      "updated_at": 1771097740
    },
    "tcp|google-h1|eth:Ethernet": {
      "success_count": 0,
      "fail_count": 3,
      "last_rtt_ms": 0,
      "score": 0,
      "updated_at": 1771097740
    },
    "tcp|google-h2|eth:Ethernet": {
      "success_count": 46,
      "fail_count": 3,
      "last_rtt_ms": 0,
      "score": 0.9387755102040817,
      "updated_at": 1771157143
    },
    "tcp|gstatic-h2|eth:Ethernet": {
      "success_count": 0,
      "fail_count": 3,
      "last_rtt_ms": 0,
      "score": 0,
      "updated_at": 1771097740
    },
    "tcp|play-h2|eth:Ethernet": {
      "success_count": 0,
      "fail_count": 3,
      "last_rtt_ms": 0,
      "score": 0,
      "updated_at": 1771097740
    },
    "tcp|youtube-h2|eth:Ethernet": {
      "success_count": 0,
      "fail_count": 3,
      "last_rtt_ms": 0,
      "score": 0,
      "updated_at": 1771097740
    }
  }
}